[
	{
		"name": "ARF",
		"hash": "KrTAtoZ+QxrJS8tl0n/uVwS1i+c="
	},
	{
		"name": "ARFR",
		"hash": "Zi1mcHA34vbUUIt7FAHczuA9z7g="
	},
	{
		"name": "CH",
		"hash": "CDVFJGepW4ZTFd0Znp0FnzVHUW4="
	},
	{
		"name": "GH",
		"hash": "70zxwotFvBVMY0G9PhtmDqE8QbI="
	},
	{
		"name": "HG",
		"hash": "82aWIzRYmYYJgBFpa/k9uDGZRRM="
	},
	{
		"name": "HS",
		"hash": "aSbnSMkCbHgqYxyDI6LGd5rpZtA="
	},
	{
		"name": "HZ",
		"hash": "NA2yitrPKQvB1bBpBFgDtVp8Lt0="
	},
	{
		"name": "JH",
		"hash": "elEYA9YS4W7XEi/UKGPuC5y2WfA="
	},
	{
		"name": "PC",
		"hash": "d00+SiQ8s5tUc/28YpGbYDvVajI="
	},
	{
		"name": "ZG",
		"hash": "runj7sdCfu6eNcLbr3fT8Cdyj7k="
	},
	{
		"name": "ZGE",
		"hash": "cLG+ooek7gmsSv71XdNHISiC3D0="
	},
	{
		"name": "ZH",
		"hash": "nM6Kl3PXn4vwsO6ziZNNRHDPEIU="
	},
	{
		"name": "ZHG",
		"hash": "uPbJRjXEAJX8EtkwxqFxpwffBhk="
	},
	{
		"name": "ZHH",
		"hash": "SfMBMuQcZwD22fGDaO/6BpJuR5U="
	},
	{
		"name": "ZHJ",
		"hash": "HOOhlWtnxNY5oSeKap1mLDpwrQI="
	},
	{
		"name": "ZHR",
		"hash": "3QEqwEyG4A4bh44ksPD2FA6jNGk="
	},
	{
		"name": "ZHSP",
		"hash": "KRbopk3pE5ew9FtLfY0EE8mrtRY="
	}
]